bluep/__init__.py
bluep/auth.py
bluep/bluep.py
bluep/cert_generator.py
bluep/config.py
bluep/middleware.py
bluep/models.py
bluep/secure_config.py
bluep/session_manager.py
bluep/websocket_manager.py
bluep-0.4.7.dist-info/METADATA
bluep-0.4.7.dist-info/WHEEL
bluep-0.4.7.dist-info/entry_points.txt
bluep-0.4.7.dist-info/RECORD
