Metadata-Version: 2.3
Name: bluep
Version: 0.4.7
Summary: A minimal real-time collaborative text editor
Author-email: GlassOnTin <63980135+GlassOnTin@users.noreply.github.com>
Requires-Python: >=3.8
Requires-Dist: cryptography>=44.0.0
Requires-Dist: fastapi>=0.68.0
Requires-Dist: httpx>=0.28.0
Requires-Dist: jinja2>=3.1.4
Requires-Dist: markupsafe>=3.0.2
Requires-Dist: mypy>=1.0.0
Requires-Dist: pillow>=8.0.0
Requires-Dist: pydantic>=1.10.0
Requires-Dist: pyotp>=2.9.0
Requires-Dist: pytest-asyncio>=0.21.0
Requires-Dist: pytest-cov>=4.0.0
Requires-Dist: pytest>=7.0.0
Requires-Dist: python-multipart>=0.0.6
Requires-Dist: qrcode>=8.0.0
Requires-Dist: tomli-w>=1.1.0
Requires-Dist: tomli>=2.2.1
Requires-Dist: types-cryptography
Requires-Dist: types-pillow
Requires-Dist: uvicorn>=0.15.0
Requires-Dist: websockets>=10.0
